Vipc/__init__.py
Vipc-0.1.3.dist-info/METADATA
Vipc-0.1.3.dist-info/RECORD
Vipc-0.1.3.dist-info/WHEEL
Vipc-0.1.3.dist-info/top_level.txt
