Metadata-Version: 2.1
Name: Vipc
Version: 0.1.3
Summary: command line tool for auto tuner
Home-page: https://github.com/ly1016799291/ceshi.git
Author: liyang
Author-email: 1016799291@qq.com
License: UNKNOWN
Platform: UNKNOWN
Classifier: Programming Language :: Python :: 3
Classifier: License :: OSI Approved :: MIT License
Classifier: Operating System :: OS Independent
